banner_baechu805/__init__.py
banner_baechu805/banner.py
banner_baechu805-0.2.3.dist-info/METADATA
banner_baechu805-0.2.3.dist-info/WHEEL
banner_baechu805-0.2.3.dist-info/entry_points.txt
banner_baechu805-0.2.3.dist-info/top_level.txt
banner_baechu805-0.2.3.dist-info/RECORD
