Metadata-Version: 2.1
Name: banner_baechu805
Version: 0.2.3
Summary: Banner Output Program
Author-email: baechu805 <bjoo606@naver.com>
License: MIT
Project-URL: Homepage, https://github.com/baechu805/banner_baechu805
Project-URL: Issues, https://github.com/baechu805/banner_baechu805/issues
Requires-Python: >=3.9
Requires-Dist: pyfiglet >=1.0.2
